ExpectException-0.1.1.dist-info/DESCRIPTION.rst
ExpectException-0.1.1.dist-info/METADATA
ExpectException-0.1.1.dist-info/RECORD
ExpectException-0.1.1.dist-info/WHEEL
ExpectException-0.1.1.dist-info/metadata.json
ExpectException-0.1.1.dist-info/top_level.txt
expectexception/__init__.py
expectexception/excpectexceptionmagic.py
